Metadata-Version: 2.1
Name: fastupdate
Version: 0.1.1
Summary: fastupdate
Home-page: https://github.com/amorgan/fastupdate
Author: Nicholas King
Author-email: amorgan@martin.info
License: MIT
Platform: UNKNOWN
Requires-Python: >=3.6
